textbox/__init__.py
textbox/config/__init__.py
textbox/config/configurator.py
textbox/data/__init__.py
textbox/data/utils.py
textbox/data/dataloader/__init__.py
textbox/data/dataloader/abstract_dataloader.py
textbox/data/dataloader/attr_sent_dataloader.py
textbox/data/dataloader/multi_sent_dataloader.py
textbox/data/dataloader/paired_sent_dataloader.py
textbox/data/dataloader/single_sent_dataloader.py
textbox/data/dataset/__init__.py
textbox/data/dataset/abstract_dataset.py
textbox/data/dataset/attr_sent_dataset.py
textbox/data/dataset/dataset.py
textbox/data/dataset/multi_sent_dataset.py
textbox/data/dataset/paired_sent_dataset.py
textbox/data/dataset/single_sent_dataset.py
textbox/evaluator/__init__.py
textbox/evaluator/abstract_evaluator.py
textbox/evaluator/dialog_evaluator.py
textbox/evaluator/metrics.py
textbox/evaluator/ngram_evaluator.py
textbox/evaluator/summarization_evaluator.py
textbox/evaluator/translation_evaluator.py
textbox/model/__init__.py
textbox/model/abstract_generator.py
textbox/model/init.py
textbox/model/Attribute/__init__.py
textbox/model/Attribute/attr2seq.py
textbox/model/Attribute/c2s.py
textbox/model/GAN/__init__.py
textbox/model/GAN/leakgan.py
textbox/model/GAN/maligan.py
textbox/model/GAN/maskgan.py
textbox/model/GAN/rankgan.py
textbox/model/GAN/seqgan.py
textbox/model/GAN/textgan.py
textbox/model/LM/__init__.py
textbox/model/LM/gpt2.py
textbox/model/LM/rnn.py
textbox/model/LM/xlnet.py
textbox/model/Seq2Seq/__init__.py
textbox/model/Seq2Seq/bart.py
textbox/model/Seq2Seq/bert2bert.py
textbox/model/Seq2Seq/hred.py
textbox/model/Seq2Seq/prophetnet.py
textbox/model/Seq2Seq/rnnencdec.py
textbox/model/Seq2Seq/t5.py
textbox/model/Seq2Seq/transformerencdec.py
textbox/model/VAE/__init__.py
textbox/model/VAE/cnnvae.py
textbox/model/VAE/cvae.py
textbox/model/VAE/hybridvae.py
textbox/model/VAE/rnnvae.py
textbox/module/__init__.py
textbox/module/layers.py
textbox/module/strategy.py
textbox/module/Attention/__init__.py
textbox-0.2.1.dist-info/LICENSE
textbox-0.2.1.dist-info/METADATA
textbox-0.2.1.dist-info/WHEEL
textbox-0.2.1.dist-info/top_level.txt
textbox-0.2.1.dist-info/RECORD
