Metadata-Version: 2.1
Name: textbox
Version: 0.2.1
Summary: A package for building text generation systems
Home-page: https://github.com/RUCAIBox/TextBox
Author: TextBoxTeam
Author-email: rucaibox@163.com
License: UNKNOWN
Platform: UNKNOWN
Requires-Python: >=3.6.2
Requires-Dist: matplotlib (>=3.1.3)
Requires-Dist: torch (>=1.6.0)
Requires-Dist: numpy (>=1.17.2)
Requires-Dist: nltk (>=3.4.5)
Requires-Dist: pyyaml (>=5.3.1)
Requires-Dist: fast-bleu (>=0.0.89)
Requires-Dist: py-rouge (>=1.1)
Requires-Dist: transformers (>=4.0.1)
Requires-Dist: tqdm (>=4.42.1)
Requires-Dist: sentencepiece (>=0.1.95)
